arflow/__init__.py
arflow/core.py
arflow/replay.py
arflow/serve.py
arflow/service_pb2.py
arflow/service_pb2.pyi
arflow/service_pb2_grpc.py
arflow-0.3.0.dist-info/entry_points.txt
arflow-0.3.0.dist-info/METADATA
arflow-0.3.0.dist-info/WHEEL
arflow-0.3.0.dist-info/RECORD
