Metadata-Version: 2.1
Name: arflow
Version: 0.3.0
Summary: ARFlow is a data-sharing layer that enables developer-friendly data streaming, storage, and visualization for augmented reality (AR) device data.
Home-page: https://cake.wpi.edu/ARFlow/
License: GPL-3.0
Author: Yiqin Zhao
Author-email: yiqinzhao@outlook.com
Requires-Python: >=3.9,<3.13
Classifier: License :: OSI Approved :: GNU General Public License v3 (GPLv3)
Classifier: Programming Language :: Python :: 3
Classifier: Programming Language :: Python :: 3.9
Classifier: Programming Language :: Python :: 3.10
Classifier: Programming Language :: Python :: 3.11
Classifier: Programming Language :: Python :: 3.12
Requires-Dist: grpcio (>=1.60.1,<2.0.0)
Requires-Dist: grpcio-tools (>=1.60.1,<2.0.0)
Requires-Dist: rerun-sdk (>=0.12.1,<0.13.0)
Project-URL: Paper, https://doi.org/10.1145/3638550.3643617
Project-URL: Repository, https://github.com/cake-lab/ARFlow
Project-URL: Video, https://youtu.be/mml8YrCgfTk
